{
  "name": "minimal-techno",
  "genre": "techno",
  "pattern": "// techno pattern in E at 128 BPM\nsetcpm(128)\n\nstack(\n  // Drums\n  s(\"bd*4, ~ cp ~ cp, hh*8\"),\n  \n  // Bass\n  note(\"E2 E2 E2 E2\").s(\"sawtooth\").cutoff(800),\n  \n  // Chords\n  note(\"<em C# G# D#>\").s(\"sawtooth\").struct(\"1 ~ 1 ~\").release(0.1).gain(0.6),\n  \n  // Melody\n  note(\"e4 b5 c4 b4 c4 b3 a3 b4\").s(\"triangle\").struct(\"~ 1 ~ 1 1 ~ 1 ~\").delay(0.25).room(0.3).gain(0.5)\n).gain(0.8)",
  "bpm": 128,
  "key": "E",
  "description": "Minimal techno with subtle groove",
  "tags": [
    "techno",
    "minimal techno"
  ],
  "timestamp": "2026-02-01T00:57:36.141Z"
}